qensfit/__init__.py
qensfit/plotcycler.py
qensfit/qensfit.py
qensfit-0.0.43.dist-info/licenses/LICENSE
qensfit-0.0.43.dist-info/METADATA
qensfit-0.0.43.dist-info/WHEEL
qensfit-0.0.43.dist-info/top_level.txt
qensfit-0.0.43.dist-info/RECORD
