Metadata-Version: 2.4
Name: qensfit
Version: 0.0.43
Summary: A library for fitting Quasielastic Neutron Scattering data.
Author-email: Antonino Caliò <antoniocalio95@gmail.com>
License:                     GNU GENERAL PUBLIC LICENSE
Project-URL: Homepage, https://github.com/antoniocalio95/qensfit
Project-URL: Documentation, https://qensfit.readthedocs.io/
License-File: LICENSE
Requires-Dist: numpy
Requires-Dist: scipy
Requires-Dist: pandas
Requires-Dist: matplotlib
Requires-Dist: alive_progress
Dynamic: license-file
